{
 "presentation": {
  "innerHtml": "Сценарий (тип 3)\n<br>1. На экране появляется формулировка задания и таймер обратного отсчета. (3-2-1-0)\n<br>    2. На экране одновременно появляется знак и надпись «Запись» синего цвета. \n       Через 1 секунду автоматически начинается запись, \n       и надпись «Запись» начинает мигать. Далее знаки появляются по одному.\n<br>    3. Студент озвучивает появившуюся на экране букву или звук в микрофон. \n       Время распознавания – не более 4 секунд. Если студент озвучил букву \n       или звук раньше 4 секунд, то программа реагирует на тишину \n       и начинает проверку автоматически.\n<br>    4. В случае правильного ответа знак загорается зеленым цветом \n       и на экране появляется следующий знак. В случае неправильного ответа \n       знак загорается оранжевым и остается на экране.\n<br>    5. «Правильный ответ» становится активным после первой неудачной попытки.\n<br>    6. Нажатие «Правильный ответ» блокирует запись, и диктор произносит \n       правильный вариант. Начинает мигать надпись «Запись», и одновременно начинается запись.\n<br>    7. После окончания выполнения упражнения становятся активными кнопки «Повторить» и «Далее». \n<br>"
 },
 "inputs": {
  "type": "card",
  "children": [
   {
    "type": "html",
    "classes": "",
    "precondition": "none",
    "hideOnCorrect": true,
    "duration": "1",
    "innerHtml": "4"
   },
   {
    "type": "html",
    "classes": "",
    "precondition": "beforeCorrect",
    "hideOnCorrect": true,
    "duration": "1",
    "innerHtml": "3"
   },
   {
    "type": "html",
    "classes": "",
    "precondition": "beforeCorrect",
    "hideOnCorrect": true,
    "duration": "1",
    "innerHtml": "2"
   },
   {
    "type": "html",
    "classes": "",
    "precondition": "beforeCorrect",
    "hideOnCorrect": true,
    "duration": "1",
    "innerHtml": "1"
   },
   {
    "type": "html",
    "classes": "",
    "precondition": "beforeCorrect",
    "hideOnCorrect": true,
    "duration": "1",
    "innerHtml": "0"
   },
   {
    "type": "card",
    "classes": "",
    "arrange": "horizontal",
    "taskPassScore": 1,
    "precondition": "beforeCorrect",
    "customtest": "",
    "maxScore": 1,
    "hideOnCorrect": true,
    "children": [
     {
      "type": "html",
      "classes": "",
      "precondition": "none",
      "hideOnCorrect": false,
      "duration": 0,
      "innerHtml": "a"
     },
     {
      "type": "recorder",
      "classes": "nowords",
      "precondition": "none",
      "autostart": false,
      "autocheck": false,
      "text": "a",
      "hideOnCorrect": false,
      "duration": 30,
      "taskPassScore": "0.6"
     }
    ],
    "autocheck": true
   },
   {
    "type": "card",
    "classes": "",
    "arrange": "horizontal",
    "taskPassScore": 1,
    "precondition": "beforeCorrect",
    "customtest": "",
    "maxScore": 1,
    "hideOnCorrect": true,
    "children": [
     {
      "type": "html",
      "classes": "",
      "precondition": "none",
      "hideOnCorrect": false,
      "duration": 0,
      "innerHtml": "b"
     },
     {
      "type": "recorder",
      "classes": "nowords",
      "precondition": "none",
      "autostart": false,
      "autocheck": false,
      "text": "b",
      "hideOnCorrect": false,
      "duration": 30,
      "taskPassScore": "0.6"
     }
    ],
    "autocheck": true
   },
   {
    "type": "card",
    "classes": "",
    "arrange": "horizontal",
    "taskPassScore": 1,
    "precondition": "beforeCorrect",
    "customtest": "",
    "maxScore": 1,
    "hideOnCorrect": false,
    "children": [
     {
      "type": "html",
      "classes": "",
      "precondition": "none",
      "hideOnCorrect": false,
      "duration": 0,
      "innerHtml": "c"
     },
     {
      "type": "recorder",
      "classes": "nowords",
      "precondition": "none",
      "autostart": false,
      "autocheck": false,
      "text": "c",
      "hideOnCorrect": false,
      "duration": 30,
      "taskPassScore": "0.6"
     }
    ],
    "autocheck": true
   }
  ],
  "classes": "",
  "arrange": "vertical",
  "taskPassScore": 1,
  "precondition": "none",
  "customtest": "",
  "maxScore": 1,
  "hideOnCorrect": false,
  "autocheck": true
 }
}