{
 "presentation": {
  "innerHtml": "8. Сгруппируйте буквы и соответствующие им знаки транскрипции"
 },
 "inputs": {
  "type": "card",
  "children": [
   {
    "type": "card",
    "classes": "",
    "arrange": "horizontal",
    "taskPassScore": 1,
    "precondition": "none",
    "customtest": "",
    "maxScore": 1,
    "hideOnCorrect": false,
    "children": [
     {
      "type": "card",
      "classes": "",
      "arrange": "horizontal",
      "taskPassScore": 1,
      "precondition": "none",
      "customtest": "",
      "maxScore": 1,
      "hideOnCorrect": false,
      "children": [
       {
        "type": "html",
        "classes": "bukva",
        "precondition": "none",
        "hideOnCorrect": false,
        "duration": 0,
        "innerHtml": "A",
        "animationFrame": true
       },
       {
        "type": "dropzone",
        "classes": "",
        "precondition": "none",
        "test": "testSet",
        "hideOnCorrect": false,
        "ejectCounterOnError": true,
        "pattern": "a\næ",
        "size": "5",
        "multiple": true
       }
      ]
     },
     {
      "type": "card",
      "classes": "",
      "arrange": "horizontal",
      "taskPassScore": 1,
      "precondition": "none",
      "customtest": "",
      "maxScore": 1,
      "hideOnCorrect": false,
      "children": [
       {
        "type": "html",
        "classes": "bukva",
        "precondition": "none",
        "hideOnCorrect": false,
        "duration": 0,
        "innerHtml": "G",
        "animationFrame": true
       },
       {
        "type": "dropzone",
        "classes": "",
        "precondition": "none",
        "test": "testSet",
        "hideOnCorrect": false,
        "ejectCounterOnError": true,
        "pattern": "g\ng",
        "size": "5",
        "multiple": true
       }
      ]
     }
    ]
   },
   {
    "type": "card",
    "classes": "",
    "arrange": "horizontal",
    "taskPassScore": 1,
    "precondition": "none",
    "customtest": "",
    "maxScore": 1,
    "hideOnCorrect": false,
    "children": [
     {
      "type": "counter",
      "classes": "",
      "precondition": "none",
      "innerHtml": "g",
      "value": ""
     },
     {
      "type": "counter",
      "classes": "",
      "precondition": "none",
      "innerHtml": "a",
      "value": ""
     },
     {
      "type": "counter",
      "classes": "",
      "precondition": "none",
      "innerHtml": "[æ]",
      "value": "æ"
     },
     {
      "type": "counter",
      "classes": "",
      "precondition": "none",
      "innerHtml": "[g]",
      "value": "g"
     }
    ]
   }
  ],
  "classes": "",
  "arrange": "vertical",
  "taskPassScore": 1,
  "precondition": "none",
  "customtest": "",
  "maxScore": 1,
  "hideOnCorrect": false
 }
}